sksurgerydavinci/__init__.py
sksurgerydavinci/__main__.py
sksurgerydavinci/_version.py
sksurgerydavinci/davinci_xi_auto_cropping.py
sksurgerydavinci/ui/__init__.py
sksurgerydavinci/ui/gui.py
sksurgerydavinci/ui/sksurgerydavinci_command_line.py
sksurgerydavinci/ui/sksurgerydavinci_demo.py
sksurgerydavinci/widgets/Viewers.py
sksurgerydavinci/widgets/__init__.py
scikit_surgerydavinci-0.3.2.dist-info/LICENSE
scikit_surgerydavinci-0.3.2.dist-info/METADATA
scikit_surgerydavinci-0.3.2.dist-info/WHEEL
scikit_surgerydavinci-0.3.2.dist-info/entry_points.txt
scikit_surgerydavinci-0.3.2.dist-info/top_level.txt
scikit_surgerydavinci-0.3.2.dist-info/RECORD
